<def-group>
  <definition class="compliance" id="sshd_do_not_permit_user_env" version="1">
    <metadata>
      <title>Do Not Allow Users to Set Environment Options</title>
      <affected family="unix">
        <platform>multi_platform_rhel</platform>
      </affected>
      <description>PermitUserEnvironment should be disabled</description>
    </metadata>
    <criteria comment="SSH is not installed or conditions are met"
    operator="OR">
      <extend_definition comment="sshd is not required and not installed, or requirement is unset"
      definition_ref="sshd_not_required_or_unset" />
      <criteria comment="sshd is installed and configured" operator="AND">
        <extend_definition comment="sshd is required and installed, or requirement is unset"
        definition_ref="sshd_required_or_unset" />
        <criterion comment="Check PermitUserEnvironment in /etc/ssh/sshd_config"
        negate="true" test_ref="test_sshd_no_user_envset" />
      </criteria>
    </criteria>
  </definition>
  <ind:textfilecontent54_test check="all" check_existence="none_exist"
  comment="Check value of PermitUserEnvironment in /etc/ssh/sshd_config"
  id="test_sshd_no_user_envset" version="1">
    <ind:object object_ref="obj_sshd_no_user_envset" />
  </ind:textfilecontent54_test>
  <ind:textfilecontent54_object id="obj_sshd_no_user_envset" version="2">
    <ind:filepath>/etc/ssh/sshd_config</ind:filepath>
    <ind:pattern operation="pattern match">^[\s]*(?i)PermitUserEnvironment(?-i)[\s]+no[\s]*(?:|(?:#.*))?$</ind:pattern>
    <ind:instance datatype="int">1</ind:instance>
  </ind:textfilecontent54_object>
</def-group>
