<Profile id="stig-rhel7-disa">
<title>DISA STIG for Red Hat Enterprise Linux 7</title>
<description>
This profile contains configuration checks that align to the 
DISA STIG for Red Hat Enterprise Linux V1R1.

In addition to being applicable to RHEL7, DISA recognizes this 
configuration baseline as applicable to the operating system
tier of Red Hat technologies that are based off RHEL7, such as RHEL
Server,  RHV-H, RHEL for HPC, RHEL Workstation, and Red Hat 
Storage deployments.
</description>

<!-- DISA FSO REFINEMENT VALUES
	The following refine-values tailor this profile to DoD-specific
	settings, as deemed approriate by DISA FSO (RE71) -->
<refine-value idref="login_banner_text" selector="dod_banners" />
<refine-value idref="inactivity_timeout_value" selector="15_minutes" />
<refine-value idref="var_screensaver_lock_delay" selector="5_seconds" />
<refine-value idref="sshd_idle_timeout_value" selector="10_minutes" />
<refine-value idref="var_accounts_fail_delay" selector="4" />
<refine-value idref="var_selinux_state" selector="enforcing" />
<refine-value idref="var_selinux_policy_name" selector="targeted" />
<refine-value idref="var_password_pam_minlen" selector="15" />
<refine-value idref="var_password_pam_ocredit" selector="1" />
<refine-value idref="var_password_pam_lcredit" selector="1" />
<refine-value idref="var_password_pam_ucredit" selector="1" />
<refine-value idref="var_accounts_passwords_pam_faillock_unlock_time" selector="never" />
<refine-value idref="var_accounts_passwords_pam_faillock_fail_interval" selector="900" />
<refine-value idref="var_accounts_passwords_pam_faillock_deny" selector="3" />
<refine-value idref="var_password_pam_unix_remember" selector="5" />
<refine-value idref="var_password_pam_maxclassrepeat" selector="4" />
<refine-value idref="var_password_pam_difok" selector="8" />
<refine-value idref="var_password_pam_dcredit" selector="1" />
<refine-value idref="var_password_pam_minclass" selector="4" />
<refine-value idref="var_accounts_minimum_age_login_defs" selector="1" />
<refine-value idref="var_password_pam_maxrepeat" selector="2" />
<refine-value idref="var_accounts_maximum_age_login_defs" selector="60" />
<refine-value idref="var_account_disable_post_pw_expiration" selector="0" />
<refine-value idref="var_removable_partition" selector="dev_cdrom" />
<refine-value idref="var_auditd_action_mail_acct" selector="root" />
<refine-value idref="var_auditd_space_left_action" selector="email" />
<refine-value idref="var_accounts_user_umask" selector="077" />
<refine-value idref="var_password_pam_retry" selector="3" />
<refine-value idref="var_accounts_max_concurrent_login_sessions" selector="10" />
<refine-value idref="var_accounts_tmout" selector="10_min" />
<refine-value idref="var_time_service_set_maxpoll" selector="system_default" />
<refine-value idref="sysctl_net_ipv4_conf_all_accept_source_route_value" selector="disabled" />
<refine-value idref="sysctl_net_ipv4_conf_default_accept_source_route_value" selector="disabled" />
<refine-value idref="sysctl_net_ipv4_icmp_echo_ignore_broadcasts_value" selector="enabled" />
<refine-value idref="sysctl_net_ipv4_conf_default_accept_redirects_value" selector="disabled" />
<refine-value idref="sysctl_net_ipv6_conf_all_accept_source_route_value" selector="disabled" />
<refine-value idref="sysctl_net_ipv4_conf_all_accept_redirects_value" selector="disabled" />

<!-- RULE ENABLEMENT -->

<!-- SRG-OS-000257-GPOS-00098, SV-86473r2_rule, RHEL-07-010010 -->
<select idref="rpm_verify_permissions" selected="true" />
<select idref="rpm_verify_ownership" selected="true" />

<!-- SRG-OS-000480-GPOS-00227, SV-86479r2_rule, RHEL-07-010020 -->
<select idref="rpm_verify_hashes" selected="true" />

<!-- SRG-OS-000023-GPOS-00006, SV-86483r2_rule, RHEL-07-010030 -->
<select idref="dconf_gnome_banner_enabled" selected="true" />

<!-- SRG-OS-000023-GPOS-00006, SV-86485r2_rule, RHEL-07-010040 -->
<select idref="dconf_gnome_login_banner_text" selected="true" />

<!-- SRG-OS-000023-GPOS-00006, SV-86487r1_rule, RHEL-07-010050 -->
<select idref="banner_etc_issue" selected="true" />

<!-- SRG-OS-000028-GPOS-00009, SV-86515r2_rule, RHEL-07-010060 -->
<select idref="dconf_gnome_screensaver_lock_enabled" selected="true" />

<!-- SRG-OS-000029-GPOS-00010, SV-86517r2_rule, RHEL-07-010070 -->
<select idref="dconf_gnome_screensaver_idle_delay" selected="true" />

<!-- SRG-OS-000029-GPOS-00010, SV-86519r3_rule, RHEL-07-010080 -->
<!-- TO DO -->

<!-- SRG-OS-000029-GPOS-00010, SV-86521r1_rule, RHEL-07-010090 -->
<select idref="package_screen_installed" selected="true" />

<!-- SRG-OS-000029-GPOS-00010, SV-86523r1_rule, RHEL-07-010100 -->
<select idref="dconf_gnome_screensaver_idle_activation_enabled" selected="true" />

<!-- SRG-OS-000029-GPOS-00010, SV-86525r1_rule, RHEL-07-010110 -->
<select idref="dconf_gnome_screensaver_lock_delay" selected="true" />

<!-- SRG-OS-000069-GPOS-00037, SV-86527r2_rule, RHEL-07-010120 -->
<select idref="accounts_password_pam_ucredit" selected="true" />

<!-- SRG-OS-000070-GPOS-00038, SV-86529r2_rule, RHEL-07-010130 -->
<select idref="accounts_password_pam_lcredit" selected="true" />

<!-- SRG-OS-000071-GPOS-00039, SV-86531r2_rule, RHEL-07-010140 -->
<select idref="accounts_password_pam_dcredit" selected="true" />

<!-- SRG-OS-000266-GPOS-00101, SV-86533r1_rule, RHEL-07-010150 -->
<select idref="accounts_password_pam_ocredit" selected="true" />

<!-- SRG-OS-000072-GPOS-00040, SV-86535r1_rule, RHEL-07-010160 -->
<select idref="accounts_password_pam_difok" selected="true" />

<!-- SRG-OS-000072-GPOS-00040, SV-86537r1_rule, RHEL-07-010170 -->
<select idref="accounts_password_pam_minclass" selected="true" />

<!-- SRG-OS-000072-GPOS-00040, SV-86539r1_rule, RHEL-07-010180 -->
<select idref="accounts_password_pam_maxrepeat" selected="true" />

<!-- SRG-OS-000072-GPOS-00040, SV-86541r1_rule, RHEL-07-010190 -->
<select idref="accounts_password_pam_maxclassrepeat" selected="true" />

<!-- SRG-OS-000073-GPOS-00041, SV-86543r1_rule, RHEL-07-010200 -->
<select idref="set_password_hashing_algorithm_systemauth" selected="true" />

<!-- SRG-OS-000073-GPOS-00041, SV-86545r1_rule, RHEL-07-010210 -->
<select idref="set_password_hashing_algorithm_logindefs" selected="true" />

<!-- SRG-OS-000073-GPOS-00041, SV-86547r2_rule, RHEL-07-010220 -->
<select idref="set_password_hashing_algorithm_libuserconf" selected="true" />

<!-- SRG-OS-000075-GPOS-00043, SV-86549r1_rule, RHEL-07-010230 -->
<select idref="accounts_minimum_age_login_defs" selected="true" />

<!-- SRG-OS-000075-GPOS-00043, SV-86551r1_rule, RHEL-07-010240 -->
<!-- TO DO -->

<!-- SRG-OS-000076-GPOS-00044, SV-86553r1_rule, RHEL-07-010250 -->
<select idref="accounts_maximum_age_login_defs" selected="true" />

<!-- SRG-OS-000076-GPOS-00044, SV-86555r1_rule, RHEL-07-010260 -->
<!-- TO DO -->

<!-- SRG-OS-000077-GPOS-00045, SV-86557r1_rule, RHEL-07-010270 -->
<select idref="accounts_password_pam_unix_remember" selected="true" />

<!-- SRG-OS-000078-GPOS-00046, SV-86559r1_rule, RHEL-07-010280 -->
<select idref="accounts_password_pam_minlen" selected="true" />

<!-- SRG-OS-000480-GPOS-00227, SV-86561r1_rule, RHEL-07-010290 -->
<select idref="no_empty_passwords" selected="true" />

<!-- SRG-OS-000106-GPOS-00053, SV-86563r2_rule, RHEL-07-010300 -->
<select idref="sshd_disable_empty_passwords" selected="true" />

<!-- SRG-OS-000118-GPOS-00060, SV-86565r1_rule, RHEL-07-010310 -->
<select idref="account_disable_post_pw_expiration" selected="true" />

<!-- SRG-OS-000329-GPOS-00128, SV-86567r2_rule, RHEL-07-010320 -->
<select idref="accounts_passwords_pam_faillock_unlock_time" selected="true" />

<!-- placeholder until DISA fixes their content:
     https://github.com/OpenSCAP/scap-security-guide/issues/1896 -->
<select idref="accounts_passwords_pam_faillock_interval" selected="true" />

<!-- placeholder until DISA fixes their content:
     https://github.com/OpenSCAP/scap-security-guide/issues/1895 -->
<select idref="accounts_passwords_pam_faillock_deny" selected="true" />

<!-- SRG-OS-000329-GPOS-00128, SV-86569r1_rule, RHEL-07-010330 -->
<select idref="accounts_passwords_pam_faillock_deny_root" selected="true" />

<!-- SRG-OS-000373-GPOS-00156, SV-86571r1_rule, RHEL-07-010340 -->
<select idref="sudo_remove_nopasswd" selected="true" />

<!-- SRG-OS-000373-GPOS-00156, SV-86573r2_rule, RHEL-07-010350 -->
<select idref="sudo_remove_no_authenticate" selected="true" />

<!-- SRG-OS-000480-GPOS-00226, SV-86575r1_rule, RHEL-07-010430 -->
<select idref="accounts_logon_fail_delay" selected="true" />

<!-- SRG-OS-000480-GPOS-00229, SV-86577r1_rule, RHEL-07-010440 -->
<select idref="gnome_gdm_disable_automatic_login" selected="true" />

<!-- SRG-OS-000480-GPOS-00229, SV-86579r2_rule, RHEL-07-010450 -->
<select idref="gnome_gdm_disable_guest_login" selected="true" />

<!-- SRG-OS-000480-GPOS-00229, SV-86581r2_rule, RHEL-07-010460 -->
<select idref="sshd_do_not_permit_user_env" selected="true" />

<!-- SRG-OS-000480-GPOS-00229, SV-86583r2_rule, RHEL-07-010470 -->
<select idref="disable_host_auth" selected="true" />

<!-- SRG-OS-000080-GPOS-00048, SV-86585r1_rule, RHEL-07-010480 -->
<select idref="bootloader_password" selected="true" />

<!-- SRG-OS-000080-GPOS-00048, SV-86587r1_rule, RHEL-07-010490 -->
<select idref="bootloader_uefi_password" selected="true" />

<!-- SRG-OS-000104-GPOS-00051, SV-86589r1_rule, RHEL-07-010500 -->
<select idref="smartcard_auth" selected="true" />

<!-- SRG-OS-000095-GPOS-00049, SV-86591r1_rule, RHEL-07-020000 -->
<select idref="package_rsh-server_removed" selected="true" />

<!-- SRG-OS-000095-GPOS-00049, SV-86593r1_rule, RHEL-07-020010 -->
<select idref="package_ypserv_removed" selected="true" />

<!-- SRG-OS-000324-GPOS-00125, SV-86595r1_rule, RHEL-07-020020 -->
<!-- TO DO -->

<!-- SRG-OS-000363-GPOS-00150, SV-86597r1_rule, RHEL-07-020030 -->
<select idref="package_aide_installed" selected="true" />
<select idref="aide_periodic_cron_checking" selected="true" />

<!-- SRG-OS-000363-GPOS-00150, SV-86599r1_rule, RHEL-07-020040 -->
<select idref="aide_scan_notification" selected="true" />

<!-- SRG-OS-000366-GPOS-00153, SV-86601r1_rule, RHEL-07-020050 -->
<select idref="ensure_gpgcheck_globally_activated" selected="true" />

<!-- SRG-OS-000366-GPOS-00153, SV-86603r1_rule, RHEL-07-020060 -->
<select idref="ensure_gpgcheck_local_packages" selected="true" />

<!-- SRG-OS-000366-GPOS-00153, SV-86605r1_rule, RHEL-07-020070 -->
<select idref="ensure_gpgcheck_repo_metadata" selected="true" />

<!-- SRG-OS-000114-GPOS-00059, SV-86607r1_rule, RHEL-07-020100 -->
<select idref="kernel_module_usb-storage_disabled" selected="true" />

<!-- SRG-OS-000114-GPOS-00059, SV-86609r1_rule, RHEL-07-020110 -->
<select idref="service_autofs_disabled" selected="true" />

<!-- SRG-OS-000437-GPOS-00194, SV-86611r1_rule, RHEL-07-020200 -->
<select idref="clean_components_post_updating" selected="true" />

<!-- SRG-OS-000445-GPOS-00199, SV-86613r2_rule, RHEL-07-020210 -->
<select idref="selinux_state" selected="true" />

<!-- SRG-OS-000445-GPOS-00199, SV-86615r2_rule, RHEL-07-020220 -->
<select idref="selinux_policytype" selected="true" />

<!-- SRG-OS-000480-GPOS-00227, SV-86617r1_rule, RHEL-07-020230 -->
<select idref="disable_ctrlaltdel_reboot" selected="true" />

<!-- SRG-OS-000480-GPOS-00228, SV-86619r1_rule, RHEL-07-020240 -->
<select idref="accounts_umask_etc_login_defs" selected="true" />

<!-- SRG-OS-000480-GPOS-00227, SV-86621r2_rule, RHEL-07-020250 -->
<select idref="installed_OS_is_certified" selected="true" />

<!-- SRG-OS-000480-GPOS-00227, SV-86623r3_rule, RHEL-07-020260 -->
<select idref="security_patches_up_to_date" selected="true" />

<!-- SRG-OS-000480-GPOS-00227, SV-86625r1_rule, RHEL-07-020270 -->

<!-- SRG-OS-000104-GPOS-00051, SV-86627r1_rule, RHEL-07-020300 -->
<select idref="gid_passwd_group_same" selected="true" />

<!-- SRG-OS-000480-GPOS-00227, SV-86629r1_rule, RHEL-07-020310 -->
<select idref="accounts_no_uid_except_zero" selected="true" />

<!-- SRG-OS-000480-GPOS-00227, SV-86631r1_rule, RHEL-07-020320 -->
<select idref="no_files_unowned_by_user" selected="true" />

<!-- SRG-OS-000480-GPOS-00227, SV-86633r1_rule, RHEL-07-020330 -->
<select idref="file_permissions_ungroupowned" selected="true" />

<!-- SRG-OS-000480-GPOS-00227, SV-86635r1_rule, RHEL-07-020600 -->
<!-- TO DO -->

<!-- SRG-OS-000480-GPOS-00227, SV-86637r1_rule, RHEL-07-020610 -->
<select idref="accounts_have_homedir_login_defs" selected="true" />

<!-- SRG-OS-000480-GPOS-00227, SV-86639r1_rule, RHEL-07-020620 -->
<!-- TO DO -->

<!-- SRG-OS-000480-GPOS-00227, SV-86641r1_rule, RHEL-07-020630 -->
<!-- TO DO -->

<!-- SRG-OS-000480-GPOS-00227, SV-86643r2_rule, RHEL-07-020640 -->
<!-- TO DO -->

<!-- SRG-OS-000480-GPOS-00227, SV-86645r2_rule, RHEL-07-020650 -->
<!-- TO DO -->

<!-- SRG-OS-000480-GPOS-00227, SV-86647r1_rule, RHEL-07-020660 -->
<!-- TO DO -->

<!-- SRG-OS-000480-GPOS-00227, SV-86649r1_rule, RHEL-07-020670 -->
<!-- TO DO -->

<!-- SRG-OS-000480-GPOS-00227, SV-86651r1_rule, RHEL-07-020680 -->
<!-- TO DO -->

<!-- SRG-OS-000480-GPOS-00227, SV-86653r1_rule, RHEL-07-020690 -->
<!-- TO DO -->

<!-- SRG-OS-000480-GPOS-00227, SV-86655r2_rule, RHEL-07-020700 -->
<!-- TO DO -->

<!-- SRG-OS-000480-GPOS-00227, SV-86657r1_rule, RHEL-07-020710 -->
<!-- TO DO -->

<!-- SRG-OS-000480-GPOS-00227, SV-86659r2_rule, RHEL-07-020720 -->
<!-- TO DO -->

<!-- SRG-OS-000480-GPOS-00227, SV-86661r1_rule, RHEL-07-020730 -->
<!-- TO DO -->

<!-- SRG-OS-000480-GPOS-00227, SV-86663r1_rule, RHEL-07-020900 -->
<select idref="selinux_all_devicefiles_labeled" selected="true" />

<!-- SRG-OS-000480-GPOS-00227, SV-86665r2_rule, RHEL-07-021000 -->
<select idref="mount_option_home_nosuid" selected="true" />

<!-- SRG-OS-000480-GPOS-00227, SV-86667r1_rule, RHEL-07-021010 -->
<select idref="mount_option_nosuid_removable_partitions" selected="true" />

<!-- SRG-OS-000480-GPOS-00227, SV-86669r1_rule, RHEL-07-021020 -->
<select idref="mount_option_nosuid_remote_filesystems" selected="true" />

<!-- SRG-OS-000480-GPOS-00227, SV-86671r1_rule, RHEL-07-021030 -->
<select idref="dir_perms_world_writable_system_owned" selected="true" />

<!-- SRG-OS-000480-GPOS-00227, SV-86673r1_rule, RHEL-07-021040 -->
<!-- TO DO -->

<!-- SRG-OS-000480-GPOS-00227, SV-86675r1_rule, RHEL-07-021100 -->
<select idref="rsyslog_cron_logging" selected="true" />

<!-- SRG-OS-000480-GPOS-00227, SV-86677r1_rule, RHEL-07-021110 -->
<select idref="file_owner_cron_allow" selected="true" />

<!-- SRG-OS-000480-GPOS-00227, SV-86679r1_rule, RHEL-07-021120 -->
<select idref="file_groupowner_cron_allow" selected="true" />

<!-- SRG-OS-000480-GPOS-00227, SV-86681r1_rule, RHEL-07-021300 -->
<select idref="service_kdump_disabled" selected="true" />

<!-- SRG-OS-000480-GPOS-00227, SV-86683r1_rule, RHEL-07-021310 -->
<select idref="partition_for_home" selected="true" />

<!-- SRG-OS-000480-GPOS-00227, SV-86685r1_rule, RHEL-07-021320 -->
<select idref="partition_for_var" selected="true" />

<!-- SRG-OS-000480-GPOS-00227, SV-86687r3_rule, RHEL-07-021330 -->
<select idref="partition_for_var_log_audit" selected="true" />

<!-- SRG-OS-000480-GPOS-00227, SV-86689r1_rule, RHEL-07-021340 -->
<select idref="partition_for_tmp" selected="true" />

<!-- SRG-OS-000033-GPOS-00014, SV-86691r2_rule, RHEL-07-021350 -->
<select idref="grub2_enable_fips_mode" selected="true" />

<!-- SRG-OS-000480-GPOS-00227, SV-86693r2_rule, RHEL-07-021600 -->
<select idref="aide_verify_acls" selected="true" />

<!-- SRG-OS-000480-GPOS-00227, SV-86695r2_rule, RHEL-07-021610 -->
<select idref="aide_verify_ext_attributes" selected="true" />

<!-- SRG-OS-000480-GPOS-00227, SV-86697r2_rule, RHEL-07-021620 -->
<select idref="aide_use_fips_hashes" selected="true" />

<!-- SRG-OS-000364-GPOS-00151, SV-86699r1_rule, RHEL-07-021700 -->
<!-- TO DO -->

<!-- SRG-OS-000095-GPOS-00049, SV-86701r1_rule, RHEL-07-021710 -->
<select idref="package_telnet-server_removed" selected="true" />

<!-- SRG-OS-000038-GPOS-00016, SV-86703r1_rule, RHEL-07-030000 -->
<select idref="service_auditd_enabled" selected="true" />

<!-- SRG-OS-000046-GPOS-00022, SV-86705r1_rule, RHEL-07-030010 -->
<select idref="audit_rules_system_shutdown" selected="true" />

<!-- SRG-OS-000342-GPOS-00133, SV-86707r1_rule, RHEL-07-030300 -->
<!-- TO DO -->

<!-- SRG-OS-000342-GPOS-00133, SV-86709r1_rule, RHEL-07-030310 -->
<!-- TO DO -->

<!-- SRG-OS-000342-GPOS-00133, SV-86711r2_rule, RHEL-07-030320 -->
<!-- TO DO -->

<!-- SRG-OS-000343-GPOS-00134, SV-86713r1_rule, RHEL-07-030330 -->
<!-- TO DO -->

<!-- SRG-OS-000343-GPOS-00134, SV-86715r1_rule, RHEL-07-030340 -->
<select idref="auditd_data_retention_space_left_action" selected="true" />

<!-- SRG-OS-000343-GPOS-00134, SV-86717r2_rule, RHEL-07-030350 -->
<select idref="auditd_data_retention_action_mail_acct" selected="true" />

<!-- SRG-OS-000327-GPOS-00127, SV-86719r2_rule, RHEL-07-030360 -->
<select idref="audit_rules_privileged_commands" selected="true" />

<!-- SRG-OS-000064-GPOS-00033, SV-86721r2_rule, RHEL-07-030370 -->
<select idref="audit_rules_dac_modification_chown" selected="true" />

<!-- SRG-OS-000064-GPOS-00033, SV-86723r2_rule, RHEL-07-030380 -->
<select idref="audit_rules_dac_modification_fchown" selected="true" />

<!-- SRG-OS-000064-GPOS-00033, SV-86725r2_rule, RHEL-07-030390 -->
<select idref="audit_rules_dac_modification_lchown" selected="true" />

<!-- SRG-OS-000064-GPOS-00033, SV-86727r2_rule, RHEL-07-030400 -->
<select idref="audit_rules_dac_modification_fchownat" selected="true" />

<!-- SRG-OS-000458-GPOS-00203, SV-86729r2_rule, RHEL-07-030410 -->
<select idref="audit_rules_dac_modification_chmod" selected="true" />

<!-- SRG-OS-000458-GPOS-00203, SV-86731r2_rule, RHEL-07-030420 -->
<select idref="audit_rules_dac_modification_fchmod" selected="true" />

<!-- SRG-OS-000458-GPOS-00203, SV-86733r2_rule, RHEL-07-030430 -->
<select idref="audit_rules_dac_modification_fchmodat" selected="true" />

<!-- SRG-OS-000458-GPOS-00203, SV-86735r2_rule, RHEL-07-030440 -->
<select idref="audit_rules_dac_modification_setxattr" selected="true" />

<!-- SRG-OS-000458-GPOS-00203, SV-86737r2_rule, RHEL-07-030450 -->
<select idref="audit_rules_dac_modification_fsetxattr" selected="true" />

<!-- SRG-OS-000458-GPOS-00203, SV-86739r2_rule, RHEL-07-030460 -->
<select idref="audit_rules_dac_modification_lsetxattr" selected="true" />

<!-- SRG-OS-000458-GPOS-00203, SV-86741r2_rule, RHEL-07-030470 -->
<select idref="audit_rules_dac_modification_removexattr" selected="true" />

<!-- SRG-OS-000458-GPOS-00203, SV-86743r2_rule, RHEL-07-030480 -->
<select idref="audit_rules_dac_modification_fremovexattr" selected="true" />

<!-- SRG-OS-000458-GPOS-00203, SV-86745r2_rule, RHEL-07-030490 -->
<select idref="audit_rules_dac_modification_lremovexattr" selected="true" />

<!-- SRG-OS-000064-GPOS-00033, SV-86747r2_rule, RHEL-07-030500 -->
<select idref="audit_rules_unsuccessful_file_modification_creat" selected="true" />

<!-- SRG-OS-000064-GPOS-00033, SV-86749r2_rule, RHEL-07-030510 -->
<select idref="audit_rules_unsuccessful_file_modification_open" selected="true" />

<!-- SRG-OS-000064-GPOS-00033, SV-86751r2_rule, RHEL-07-030520 -->
<select idref="audit_rules_unsuccessful_file_modification_openat" selected="true" />

<!-- SRG-OS-000064-GPOS-00033, SV-86753r2_rule, RHEL-07-030530 -->
<select idref="audit_rules_unsuccessful_file_modification_open_by_handle_at" selected="true" />

<!-- SRG-OS-000064-GPOS-00033, SV-86755r2_rule, RHEL-07-030540 -->
<select idref="audit_rules_unsuccessful_file_modification_truncate" selected="true" />

<!-- SRG-OS-000064-GPOS-00033, SV-86757r2_rule, RHEL-07-030550 -->
<select idref="audit_rules_unsuccessful_file_modification_ftruncate" selected="true" />

<!-- SRG-OS-000392-GPOS-00172, SV-86759r3_rule, RHEL-07-030560 -->
<select idref="audit_rules_execution_semanage" selected="true" />

<!-- SRG-OS-000392-GPOS-00172, SV-86761r3_rule, RHEL-07-030570 -->
<select idref="audit_rules_execution_setsebool" selected="true" />

<!-- SRG-OS-000392-GPOS-00172, SV-86763r3_rule, RHEL-07-030580 -->
<select idref="audit_rules_execution_chcon" selected="true" />

<!-- SRG-OS-000392-GPOS-00172, SV-86765r3_rule, RHEL-07-030590 -->
<select idref="audit_rules_execution_restorecon" selected="true" />

<!-- SRG-OS-000392-GPOS-00172, SV-86767r2_rule, RHEL-07-030600 -->
<select idref="audit_rules_login_events_tallylog" selected="true" />

<!-- SRG-OS-000392-GPOS-00172, SV-86769r2_rule, RHEL-07-030610 -->
<select idref="audit_rules_login_events_faillock" selected="true" />

<!-- SRG-OS-000392-GPOS-00172, SV-86771r2_rule, RHEL-07-030620 -->
<select idref="audit_rules_login_events_lastlog" selected="true" />

<!-- SRG-OS-000042-GPOS-00020, SV-86773r3_rule, RHEL-07-030630 -->
<select idref="audit_rules_privileged_commands_passwd" selected="true" />

<!-- SRG-OS-000042-GPOS-00020, SV-86775r3_rule, RHEL-07-030640 -->
<select idref="audit_rules_privileged_commands_unix_chkpwd" selected="true" />

<!-- SRG-OS-000042-GPOS-00020, SV-86777r3_rule, RHEL-07-030650 -->
<select idref="audit_rules_privileged_commands_gpasswd" selected="true" />

<!-- SRG-OS-000042-GPOS-00020, SV-86779r3_rule, RHEL-07-030660 -->
<select idref="audit_rules_privileged_commands_chage" selected="true" />

<!-- SRG-OS-000042-GPOS-00020, SV-86781r3_rule, RHEL-07-030670 -->
<select idref="audit_rules_privileged_commands_userhelper" selected="true" />

<!-- SRG-OS-000037-GPOS-00015, SV-86783r3_rule, RHEL-07-030680 -->
<select idref="audit_rules_privileged_commands_su" selected="true" />

<!-- SRG-OS-000037-GPOS-00015, SV-86785r3_rule, RHEL-07-030690 -->
<select idref="audit_rules_privileged_commands_sudo" selected="true" />

<!-- SRG-OS-000037-GPOS-00015, SV-86787r3_rule, RHEL-07-030700 -->
<select idref="audit_rules_sysadmin_actions" selected="true" />

<!-- SRG-OS-000037-GPOS-00015, SV-86789r3_rule, RHEL-07-030710 -->
<!-- TO DO -->

<!-- SRG-OS-000037-GPOS-00015, SV-86791r3_rule, RHEL-07-030720 -->
<select idref="audit_rules_privileged_commands_chsh" selected="true" />

<!-- SRG-OS-000037-GPOS-00015, SV-86793r3_rule, RHEL-07-030730 -->
<select idref="audit_rules_privileged_commands_sudoedit" selected="true" />

<!-- SRG-OS-000042-GPOS-00020, SV-86795r3_rule, RHEL-07-030740 -->
<select idref="audit_rules_media_export" selected="true" />

<!-- SRG-OS-000042-GPOS-00020, SV-86797r3_rule, RHEL-07-030750 -->
<select idref="audit_rules_privileged_commands_umount" selected="true" />

<!-- SRG-OS-000042-GPOS-00020, SV-86799r3_rule, RHEL-07-030760 -->
<select idref="audit_rules_privileged_commands_postdrop" selected="true" />

<!-- SRG-OS-000042-GPOS-00020, SV-86801r2_rule, RHEL-07-030770 -->
<select idref="audit_rules_privileged_commands_postqueue" selected="true" />

<!-- SRG-OS-000042-GPOS-00020, SV-86803r2_rule, RHEL-07-030780 -->
<select idref="audit_rules_privileged_commands_ssh_keysign" selected="true" />

<!-- SRG-OS-000042-GPOS-00020, SV-86805r2_rule, RHEL-07-030790 -->
<select idref="audit_rules_privileged_commands_pt_chown" selected="true" />

<!-- SRG-OS-000042-GPOS-00020, SV-86807r2_rule, RHEL-07-030800 -->
<select idref="audit_rules_privileged_commands_crontab" selected="true" />

<!-- SRG-OS-000471-GPOS-00215, SV-86809r2_rule, RHEL-07-030810 -->
<select idref="audit_rules_privileged_commands_pam_timestamp_check" selected="true" />

<!-- SRG-OS-000471-GPOS-00216, SV-86811r2_rule, RHEL-07-030820 -->
<select idref="audit_rules_kernel_module_loading_init" selected="true" />

<!-- SRG-OS-000471-GPOS-00216, SV-86813r2_rule, RHEL-07-030830 -->
<select idref="audit_rules_kernel_module_loading_delete" selected="true" />

<!-- SRG-OS-000471-GPOS-00216, SV-86815r2_rule, RHEL-07-030840 -->
<select idref="audit_rules_kernel_module_loading_insmod" selected="true" />

<!-- SRG-OS-000471-GPOS-00216, SV-86817r2_rule, RHEL-07-030850 -->
<select idref="audit_rules_kernel_module_loading_rmmod" selected="true" />

<!-- SRG-OS-000471-GPOS-00216, SV-86819r2_rule, RHEL-07-030860 -->
<select idref="audit_rules_kernel_module_loading_modprobe" selected="true" />

<!-- SRG-OS-000004-GPOS-00004, SV-86821r3_rule, RHEL-07-030870 -->
<select idref="audit_rules_usergroup_modification_passwd" selected="true" />

<!-- SRG-OS-000466-GPOS-00210, SV-86823r2_rule, RHEL-07-030880 -->
<select idref="audit_rules_file_deletion_events_rename" selected="true" />

<!-- SRG-OS-000466-GPOS-00210, SV-86825r2_rule, RHEL-07-030890 -->
<select idref="audit_rules_file_deletion_events_renameat" selected="true" />

<!-- SRG-OS-000466-GPOS-00210, SV-86827r2_rule, RHEL-07-030900 -->
<select idref="audit_rules_file_deletion_events_rmdir" selected="true" />

<!-- SRG-OS-000466-GPOS-00210, SV-86829r2_rule, RHEL-07-030910 -->
<select idref="audit_rules_file_deletion_events_unlink" selected="true" />

<!-- SRG-OS-000466-GPOS-00210, SV-86831r2_rule, RHEL-07-030920 -->
<select idref="audit_rules_file_deletion_events_unlinkat" selected="true" />

<!-- SRG-OS-000480-GPOS-00227, SV-86833r1_rule, RHEL-07-031000 -->
<select idref="rsyslog_remote_loghost" selected="true" />

<!-- SRG-OS-000480-GPOS-00227, SV-86835r1_rule, RHEL-07-031010 -->
<select idref="rsyslog_nolisten" selected="true" />

<!-- SRG-OS-000480-GPOS-00227, SV-86837r1_rule, RHEL-07-032000 -->
<select idref="install_mcafee_antivirus" selected="true" />

<!-- SRG-OS-000480-GPOS-00227, SV-86839r1_rule, RHEL-07-032010 -->
<select idref="mcafee_antivirus_definitions_updated" selected="true" />

<!-- SRG-OS-000027-GPOS-00008, SV-86841r1_rule, RHEL-07-040000 -->
<select idref="accounts_max_concurrent_login_sessions" selected="true" />

<!-- SRG-OS-000096-GPOS-00050, SV-86843r1_rule, RHEL-07-040100 -->
<select idref="configure_firewalld_ports" selected="true" />

<!-- SRG-OS-000033-GPOS-00014, SV-86845r2_rule, RHEL-07-040110 -->
<select idref="sshd_use_approved_ciphers" selected="true" />

<!-- SRG-OS-000163-GPOS-00072, SV-86847r2_rule, RHEL-07-040160 -->
<select idref="accounts_tmout" selected="true" />

<!-- SRG-OS-000023-GPOS-00006, SV-86849r2_rule, RHEL-07-040170 -->
<select idref="sshd_enable_warning_banner" selected="true" />

<!-- SRG-OS-000250-GPOS-00093, SV-86851r2_rule, RHEL-07-040180 -->
<select idref="ldap_client_start_tls" selected="true" />

<!-- SRG-OS-000250-GPOS-00093, SV-86853r2_rule, RHEL-07-040190 -->
<!-- TO DO -->

<!-- SRG-OS-000250-GPOS-00093, SV-86855r2_rule, RHEL-07-040200 -->
<!-- TO DO -->

<!-- SRG-OS-000423-GPOS-00187, SV-86857r1_rule, RHEL-07-040300 -->
<select idref="package_openssh-server_installed" selected="true" />

<!-- SRG-OS-000423-GPOS-00187, SV-86859r2_rule, RHEL-07-040310 -->
<!-- Other Rules will know that SSH is required to be installed -->
<refine-value idref="sshd_required" selector="yes" />
<select idref="service_sshd_enabled" selected="true" />

<!-- SRG-OS-000163-GPOS-00072, SV-86861r2_rule, RHEL-07-040320 -->
<select idref="sshd_set_idle_timeout" selected="true" />

<!-- SRG-OS-000480-GPOS-00227, SV-86863r2_rule, RHEL-07-040330 -->
<select idref="sshd_disable_rhosts_rsa" selected="true" />

<!-- SRG-OS-000163-GPOS-00072, SV-86865r2_rule, RHEL-07-040340 -->
<select idref="sshd_set_keepalive" selected="true" />

<!-- SRG-OS-000480-GPOS-00227, SV-86867r2_rule, RHEL-07-040350 -->
<select idref="sshd_disable_rhosts" selected="true" />

<!-- SRG-OS-000480-GPOS-00227, SV-86869r2_rule, RHEL-07-040360 -->
<select idref="sshd_print_last_log" selected="true" />

<!-- SRG-OS-000480-GPOS-00227, SV-86871r2_rule, RHEL-07-040370 -->
<select idref="sshd_disable_root_login" selected="true" />

<!-- SRG-OS-000480-GPOS-00227, SV-86873r2_rule, RHEL-07-040380 -->
<select idref="sshd_disable_user_known_hosts" selected="true" />

<!-- SRG-OS-000074-GPOS-00042, SV-86875r2_rule, RHEL-07-040390 -->
<select idref="sshd_allow_only_protocol2" selected="true" />

<!-- SRG-OS-000250-GPOS-00093, SV-86877r2_rule, RHEL-07-040400 -->
<select idref="sshd_use_approved_macs" selected="true" />

<!-- SRG-OS-000480-GPOS-00227, SV-86879r1_rule, RHEL-07-040410 -->
<select idref="file_permissions_sshd_pub_key" selected="true" />

<!-- SRG-OS-000480-GPOS-00227, SV-86881r1_rule, RHEL-07-040420 -->
<select idref="file_permissions_sshd_private_key" selected="true" />

<!-- SRG-OS-000364-GPOS-00151, SV-86883r2_rule, RHEL-07-040430 -->
<select idref="sshd_disable_gssapi_auth" selected="true" />

<!-- SRG-OS-000364-GPOS-00151, SV-86885r2_rule, RHEL-07-040440 -->
<select idref="sshd_disable_kerb_auth" selected="true" />

<!-- SRG-OS-000480-GPOS-00227, SV-86887r2_rule, RHEL-07-040450 -->
<select idref="sshd_enable_strictmodes" selected="true" />

<!-- SRG-OS-000480-GPOS-00227, SV-86889r2_rule, RHEL-07-040460 -->
<select idref="sshd_use_priv_separation" selected="true" />

<!-- SRG-OS-000480-GPOS-00227, SV-86891r2_rule, RHEL-07-040470 -->
<select idref="sshd_disable_compression" selected="true" />

<!-- SRG-OS-000355-GPOS-00143, SV-86893r2_rule, RHEL-07-040500 -->
<select idref="chronyd_or_ntpd_set_maxpoll" selected="true" />

<!-- SRG-OS-000420-GPOS-00186, SV-86895r1_rule, RHEL-07-040510 -->
<!-- TO DO -->

<!-- SRG-OS-000480-GPOS-00227, SV-86897r1_rule, RHEL-07-040520 -->
<select idref="service_firewalld_enabled" selected="true" />

<!-- SRG-OS-000480-GPOS-00227, SV-86899r1_rule, RHEL-07-040530 -->
<select idref="display_login_attempts" selected="true" />

<!-- SRG-OS-000480-GPOS-00227, SV-86901r1_rule, RHEL-07-040540 -->
<!-- TO DO -->

<!-- SRG-OS-000480-GPOS-00227, SV-86903r1_rule, RHEL-07-040550 -->
<!-- TO DO -->

<!-- SRG-OS-000480-GPOS-00227, SV-86905r1_rule, RHEL-07-040600 -->
<select idref="network_configure_name_resolution" selected="true" />

<!-- SRG-OS-000480-GPOS-00227, SV-86907r1_rule, RHEL-07-040610 -->
<select idref="sysctl_net_ipv4_conf_all_accept_source_route" selected="true" />

<!-- SRG-OS-000480-GPOS-00227, SV-86909r1_rule, RHEL-07-040620 -->
<select idref="sysctl_net_ipv4_conf_default_accept_source_route" selected="true" />

<!-- SRG-OS-000480-GPOS-00227, SV-86911r1_rule, RHEL-07-040630 -->
<select idref="sysctl_net_ipv4_icmp_echo_ignore_broadcasts" selected="true" />

<!-- SRG-OS-000480-GPOS-00227, SV-86913r2_rule, RHEL-07-040640 -->
<select idref="sysctl_net_ipv4_conf_default_accept_redirects" selected="true" />

<!-- SRG-OS-000480-GPOS-00227, SV-86915r2_rule, RHEL-07-040650 -->
<select idref="sysctl_net_ipv4_conf_default_send_redirects" selected="true" />

<!-- SRG-OS-000480-GPOS-00227, SV-86917r2_rule, RHEL-07-040660 -->
<select idref="sysctl_net_ipv4_conf_all_send_redirects" selected="true" />

<!-- SRG-OS-000480-GPOS-00227, SV-86919r1_rule, RHEL-07-040670 -->
<select idref="network_sniffer_disabled" selected="true" />

<!-- SRG-OS-000480-GPOS-00227, SV-86921r2_rule, RHEL-07-040680 -->
<!-- TO DO -->

<!-- SRG-OS-000480-GPOS-00227, SV-86923r1_rule, RHEL-07-040690 -->
<select idref="package_vsftpd_removed" selected="true" />

<!-- SRG-OS-000480-GPOS-00227, SV-86925r1_rule, RHEL-07-040700 -->
<select idref="package_tftp-server_removed" selected="true" />

<!-- SRG-OS-000480-GPOS-00227, SV-86927r2_rule, RHEL-07-040710 -->
<select idref="sshd_enable_x11_forwarding" selected="true" />

<!-- SRG-OS-000480-GPOS-00227, SV-86929r1_rule, RHEL-07-040720 -->
<select idref="tftpd_uses_secure_mode" selected="true" />

<!-- SRG-OS-000480-GPOS-00227, SV-86931r2_rule, RHEL-07-040730 -->
<select idref="package_xorg-x11-server-common_removed" selected="true" />

<!-- SRG-OS-000480-GPOS-00227, SV-86933r1_rule, RHEL-07-040740 -->
<select idref="sysctl_net_ipv4_ip_forward" selected="true" />

<!-- SRG-OS-000480-GPOS-00227, SV-86935r3_rule, RHEL-07-040750 -->
<select idref="mount_option_krb_sec_remote_filesystems" selected="true" />

<!-- SRG-OS-000480-GPOS-00227, SV-86937r1_rule, RHEL-07-040800 -->
<select idref="snmpd_not_default_password" selected="true" />

<!-- SRG-OS-000480-GPOS-00227, SV-86939r1_rule, RHEL-07-040810 -->
<select idref="set_firewalld_default_zone" selected="true" />

<!-- SRG-OS-000480-GPOS-00227, SV-86941r1_rule, RHEL-07-040820 -->
<select idref="libreswan_approved_tunnels" selected="true" />

<!-- SRG-OS-000480-GPOS-00227, SV-86943r1_rule, RHEL-07-040830 -->
<select idref="sysctl_net_ipv6_conf_all_accept_source_route" selected="true" />

<!-- SRG-OS-000375-GPOS-00160, SV-87041r2_rule, RHEL-07-041001 -->
<!-- TO DO -->

<!-- SRG-OS-000375-GPOS-00160, SV-87051r2_rule, RHEL-07-041002 -->
<select idref="sssd_enable_pam_services" selected="true" />

<!-- SRG-OS-000375-GPOS-00160, SV-87057r2_rule, RHEL-07-041003 -->
<!-- TO DO -->

<!-- SRG-OS-000375-GPOS-00160, SV-87059r2_rule, RHEL-07-041004 -->
<!-- TO DO -->

<!-- SRG-OS-000029-GPOS-00010, SV-87807r2_rule, RHEL-07-010081 -->
<select idref="dconf_gnome_session_user_locks" selected="true" />

<!-- SRG-OS-000029-GPOS-00010, SV-87809r2_rule, RHEL-07-010082 -->
<!-- TO DO -->

<!-- SRG-OS-000069-GPOS-00037, SV-87811r2_rule, RHEL-07-010119 -->
<select idref="accounts_password_pam_retry" selected="true" />

<!-- SRG-OS-000480-GPOS-00227, SV-87813r1_rule, RHEL-07-021021 -->
<select idref="mount_option_noexec_remote_filesystems" selected="true" />

<!-- SRG-OS-000342-GPOS-00133, SV-87815r2_rule, RHEL-07-030321 -->
<!-- TO DO -->

<!-- SRG-OS-000004-GPOS-00004, SV-87817r2_rule, RHEL-07-030871 -->
<select idref="audit_rules_usergroup_modification_group" selected="true" />

<!-- SRG-OS-000004-GPOS-00004, SV-87819r2_rule, RHEL-07-030872 -->
<select idref="audit_rules_usergroup_modification_gshadow" selected="true" />

<!-- SRG-OS-000004-GPOS-00004, SV-87823r2_rule, RHEL-07-030873 -->
<select idref="audit_rules_usergroup_modification_shadow" selected="true" />

<!-- SRG-OS-000004-GPOS-00004, SV-87825r2_rule, RHEL-07-030874 -->
<select idref="audit_rules_usergroup_modification_opasswd" selected="true" />

<!-- SRG-OS-000480-GPOS-00227, SV-87827r2_rule, RHEL-07-040641 -->
<select idref="sysctl_net_ipv4_conf_all_accept_redirects" selected="true" />

<!-- SRG-OS-000424-GPOS-00188, SV-87829r1_rule, RHEL-07-041010 -->
<!-- TO DO -->

</Profile>
